{"lt":0,"wc":0,"lnt":1,"s":{"x":13,"y":22},"sfD":[{"p":{"x":6,"y":11},"t":141,"d":0,"m":1},{"p":{"x":8,"y":10},"t":141,"d":3,"m":1},{"p":{"x":8,"y":13},"t":141,"d":1,"m":0},{"p":{"x":7,"y":9},"t":143,"d":3,"m":2},{"p":{"x":6,"y":10},"t":143,"d":0,"m":1},{"p":{"x":9,"y":11},"t":143,"d":1,"m":1},{"p":{"x":9,"y":12},"t":143,"d":1,"m":2},{"p":{"x":5,"y":12},"t":143,"d":0,"m":0},{"p":{"x":6,"y":14},"t":143,"d":0,"m":0},{"p":{"x":6,"y":9},"t":142,"d":0,"m":0},{"p":{"x":5,"y":11},"t":142,"d":0,"m":1},{"p":{"x":8,"y":9},"t":142,"d":3,"m":1},{"p":{"x":9,"y":10},"t":142,"d":3,"m":2},{"p":{"x":9,"y":13},"t":142,"d":1,"m":1},{"p":{"x":5,"y":13},"t":142,"d":2,"m":1},{"p":{"x":6,"y":15},"t":142,"d":2,"m":0},{"p":{"x":4,"y":16},"t":143,"d":3,"m":2},{"p":{"x":5,"y":17},"t":143,"d":1,"m":2},{"p":{"x":4,"y":18},"t":143,"d":2,"m":0},{"p":{"x":3,"y":17},"t":143,"d":0,"m":0},{"p":{"x":3,"y":16},"t":142,"d":0,"m":1},{"p":{"x":5,"y":16},"t":142,"d":3,"m":1},{"p":{"x":5,"y":18},"t":142,"d":1,"m":2},{"p":{"x":3,"y":18},"t":142,"d":2,"m":0},{"p":{"x":4,"y":17},"t":140,"d":2,"m":2},{"p":{"x":6,"y":12},"t":140,"d":2,"m":0},{"p":{"x":7,"y":10},"t":140,"d":2,"m":0},{"p":{"x":7,"y":12},"t":140,"d":2,"m":2},{"p":{"x":7,"y":13},"t":140,"d":2,"m":0},{"p":{"x":8,"y":12},"t":140,"d":2,"m":2},{"p":{"x":8,"y":11},"t":140,"d":2,"m":0},{"p":{"x":7,"y":11},"t":140,"d":2,"m":0},{"p":{"x":6,"y":13},"t":140,"d":2,"m":1},{"p":{"x":8,"y":15},"t":142,"d":1,"m":1},{"p":{"x":7,"y":15},"t":143,"d":2,"m":0},{"p":{"x":8,"y":14},"t":143,"d":1,"m":2},{"p":{"x":7,"y":14},"t":140,"d":2,"m":2},{"p":{"x":7,"y":4},"t":140,"d":2,"m":2},{"p":{"x":7,"y":5},"t":140,"d":2,"m":2},{"p":{"x":6,"y":5},"t":140,"d":2,"m":2},{"p":{"x":5,"y":6},"t":142,"d":2,"m":0},{"p":{"x":9,"y":6},"t":142,"d":1,"m":1},{"p":{"x":9,"y":5},"t":142,"d":3,"m":0},{"p":{"x":8,"y":3},"t":142,"d":3,"m":0},{"p":{"x":5,"y":4},"t":142,"d":0,"m":0},{"p":{"x":6,"y":3},"t":142,"d":0,"m":0},{"p":{"x":5,"y":5},"t":143,"d":0,"m":0},{"p":{"x":6,"y":6},"t":143,"d":2,"m":0},{"p":{"x":7,"y":6},"t":143,"d":2,"m":0},{"p":{"x":8,"y":6},"t":143,"d":2,"m":0},{"p":{"x":8,"y":4},"t":143,"d":1,"m":2},{"p":{"x":8,"y":5},"t":141,"d":3,"m":1},{"p":{"x":7,"y":3},"t":143,"d":3,"m":2},{"p":{"x":6,"y":4},"t":141,"d":0,"m":1}],"uD":[{"c":{"x":6,"y":12},"t":14,"d":2},{"c":{"x":8,"y":10},"t":10,"d":2},{"c":{"x":8,"y":13},"t":10,"d":2},{"c":{"x":7,"y":18},"t":21,"d":1},{"c":{"x":9,"y":17},"t":21,"d":0},{"c":{"x":3,"y":10},"t":22,"d":3},{"c":{"x":4,"y":17},"t":13,"d":2},{"c":{"x":5,"y":13},"t":27,"d":2},{"c":{"x":3,"y":14},"t":32,"d":0},{"c":{"x":8,"y":4},"t":8,"d":3},{"c":{"x":8,"y":5},"t":14,"d":2},{"c":{"x":7,"y":5},"t":14,"d":2},{"c":{"x":6,"y":4},"t":27,"d":2},{"c":{"x":7,"y":3},"t":3,"d":2},{"c":{"x":4,"y":2},"t":21,"d":3},{"c":{"x":11,"y":4},"t":21,"d":1}],"suD":[],"htD":[{"p":{"x":11.0,"y":7.0}},{"p":{"x":13.0,"y":7.0}},{"p":{"x":15.0,"y":7.0}},{"p":{"x":17.0,"y":7.0}},{"p":{"x":17.0,"y":9.0}},{"p":{"x":15.0,"y":9.0}},{"p":{"x":13.0,"y":9.0}},{"p":{"x":13.0,"y":7.0}},{"p":{"x":13.0,"y":9.0}},{"p":{"x":13.0,"y":9.0}},{"p":{"x":11.0,"y":9.0}},{"p":{"x":9.0,"y":9.0}},{"p":{"x":7.0,"y":9.0}},{"p":{"x":7.0,"y":11.0}},{"p":{"x":9.0,"y":11.0}},{"p":{"x":11.0,"y":11.0}},{"p":{"x":11.0,"y":9.0}},{"p":{"x":11.0,"y":11.0}},{"p":{"x":11.0,"y":11.0}},{"p":{"x":9.0,"y":11.0}},{"p":{"x":9.0,"y":13.0}},{"p":{"x":11.0,"y":13.0}},{"p":{"x":13.0,"y":13.0}},{"p":{"x":15.0,"y":13.0}},{"p":{"x":17.0,"y":13.0}},{"p":{"x":17.0,"y":15.0}},{"p":{"x":17.0,"y":17.0}},{"p":{"x":17.0,"y":19.0}},{"p":{"x":17.0,"y":21.0}}],"pS":[{"x":7,"y":4,"d":2,"i":0},{"x":7,"y":5,"d":2,"i":0},{"x":9,"y":5,"d":0,"i":0},{"x":7,"y":4,"d":2,"i":0},{"x":7,"y":5,"d":2,"i":0},{"x":7,"y":6,"d":2,"i":0},{"x":8,"y":14,"d":3,"i":1},{"x":9,"y":12,"d":0,"i":1},{"x":7,"y":11,"d":2,"i":1},{"x":7,"y":12,"d":2,"i":1},{"x":8,"y":14,"d":0,"i":1},{"x":7,"y":12,"d":0,"i":1},{"x":5,"y":11,"d":2,"i":1},{"x":5,"y":12,"d":2,"i":1}]}